{
  "report_type": "GOVERNANCE_FREEZE_REPORT",
  "prompt_id": "P20_T20A_AUDIT_REMEDIATION_FREEZE_AND_GOVERNANCE_LOCK_V1",
  "status": "COMPLETED",
  "kernel_loaded": "MAZAO_EXECUTION_KERNEL_V1",
  "freeze_doc_created": true,
  "docs_updated": true,
  "readme_updated": true,
  "progress_tracker_updated": true,
  "phase_20_locked": true,
  "t9h_preserved_as_next_gate": true,
  "code_files_modified": 0,
  "healing_protocol_passed": true,
  "commit_hash": "PENDING_PUSH",
  "push_status": "PENDING",
  "known_issues": "None",
  "ready_for_next_prompt": true
}
